{
  "canonical": "https://www.cnclathing.com/edm-machining",
  "category": "service",
  "competitor": "CNCLATHING",
  "ctas": [
    {
      "href": "/quote",
      "text": "Get a Quote"
    },
    {
      "href": "",
      "text": "Get a Quote"
    },
    {
      "href": "/contact-us",
      "text": "Contact Us"
    },
    {
      "href": "/quote",
      "text": "Quote"
    },
    {
      "href": "",
      "text": "Quote"
    },
    {
      "href": "#forminator-module-16081",
      "text": "Get instant quote"
    },
    {
      "href": "/semiconductor-industry",
      "text": "Semiconductor Industry"
    },
    {
      "href": "/aerospace-industry",
      "text": "Aerospace Industry"
    },
    {
      "href": "/agricultural-industry",
      "text": "Agricultural Industry"
    },
    {
      "href": "/automotive-industry",
      "text": "Automotive Industry"
    },
    {
      "href": "/electronic-industry",
      "text": "Electronic Industry"
    },
    {
      "href": "/food-industry",
      "text": "Food industry"
    },
    {
      "href": "/high-tech-industry",
      "text": "High Tech Industry"
    },
    {
      "href": "/machine-tool-industry",
      "text": "Machine Tool Industry"
    },
    {
      "href": "/marine-industry",
      "text": "Marine Industry"
    },
    {
      "href": "/medical-industry",
      "text": "Medical Industry"
    },
    {
      "href": "/military-industry",
      "text": "Military Industry"
    }
  ],
  "fetched_at": "2026-07-20T05:04:11+00:00",
  "h1": "",
  "headings": [
    {
      "level": "h1",
      "text": "EDM Machining Services"
    },
    {
      "level": "h2",
      "text": "What is EDM Machining – Electrical Discharge Machining Definition"
    },
    {
      "level": "h2",
      "text": "Why Use EDM Machining?"
    },
    {
      "level": "h3",
      "text": "Advantages of Electrical Discharge Machining"
    },
    {
      "level": "h2",
      "text": "EDM Services – Top-Notch Electrical Discharge Machining Services"
    },
    {
      "level": "h2",
      "text": "Types of EDM Machining"
    },
    {
      "level": "h3",
      "text": "Advantages of Wire EDM"
    },
    {
      "level": "h3",
      "text": "Advantages of Die Sinking EDM"
    },
    {
      "level": "h3",
      "text": "Advantages of Hole-Drilling EDM"
    },
    {
      "level": "h2",
      "text": "EDM Machining Materials – What Materials Can Be Machined by EDM"
    },
    {
      "level": "h2",
      "text": "Applications of Electrical Discharge Machining"
    },
    {
      "level": "h2",
      "text": "When to Use EDM – When EDM Machining is Needed?"
    },
    {
      "level": "h2",
      "text": "Die Sinking EDM vs Wire EDM, What’s the Difference and Which One to Choose?"
    }
  ],
  "images": [
    {
      "alt": "",
      "src": "/images/logo.png"
    },
    {
      "alt": "",
      "src": "/wp-content/uploads/107A4771-1-jpg.webp"
    },
    {
      "alt": "",
      "src": "/images/whatsapp.png"
    },
    {
      "alt": "Relied on by",
      "src": "/images/edm-logo.jpg"
    },
    {
      "alt": "",
      "src": "/wp-content/uploads/EDM-Machining-Parts.png"
    },
    {
      "alt": "",
      "src": "/images/cnc-wire-edm.jpg"
    },
    {
      "alt": "",
      "src": "/images/die-sinking-edm.jpg"
    },
    {
      "alt": "",
      "src": "/images/edm-hole-drilling.jpg"
    },
    {
      "alt": "",
      "src": "/images/edm-hole-popping.jpg"
    },
    {
      "alt": "",
      "src": "/images/edm-machining-brass.jpg"
    },
    {
      "alt": "",
      "src": "/images/edm-machining-copper.jpg"
    },
    {
      "alt": "",
      "src": "/images/edm-machining-aluminum.jpg"
    },
    {
      "alt": "",
      "src": "/images/edm-machining-Tianium.png"
    },
    {
      "alt": "",
      "src": "/images/edm-machining-steel.png"
    },
    {
      "alt": "",
      "src": "/images/edm-machining-stainless-steel.jpg"
    },
    {
      "alt": "",
      "src": "/images/edm-machining-nickel-alloys.png"
    },
    {
      "alt": "EDM QUOTE",
      "src": "/images/edm-quote.png"
    },
    {
      "alt": "",
      "src": "/images/edm-machining-5.jpg"
    },
    {
      "alt": "",
      "src": "/images/emd-nd-1.jpg"
    },
    {
      "alt": "",
      "src": "/images/emd-nd-2.jpg"
    },
    {
      "alt": "",
      "src": "/images/emd-nd-3.jpg"
    },
    {
      "alt": "",
      "src": "/images/emd-nd-4.jpg"
    },
    {
      "alt": "Die Sinking EDM vs Wire EDM",
      "src": "/images/die-sink-wire.jpg"
    },
    {
      "alt": "certificate",
      "src": "/images/you.png"
    }
  ],
  "meta_description": "Our EDM services provide several types of EDM machining processes for producing precision EDM parts, including wire-cut EDM, sinker EDM, and hole-drilling EDM.",
  "requested_url": "https://www.cnclathing.com/edm-machining",
  "sections": [
    {
      "hash": "9a810c7d4a28ed9e5e45a17c4bc5ef6f9239c860",
      "heading": "EDM Machining Services",
      "level": "h1",
      "text": "EDM Machining Services EDM Services & Precision EDM Machining Parts – What is Electrical Discharge Machining Process. Get instant quote Machined prototypes in as fast as 1 days. Tolerances down to +-0.012mm ISO 9001:2015, CE:SHBST100665461231 Relied on by"
    },
    {
      "hash": "72b7d4ba7ce7272b60f2b044c08706b541e0b632",
      "heading": "What is EDM Machining – Electrical Discharge Machining Definition",
      "level": "h2",
      "text": "What is EDM Machining – Electrical Discharge Machining Definition Electrical discharge machining or EDM, also known as spark machining or spark eroding, is a metal fabrication process and non-traditional material-removal process to get the desired shape using electrical discharges. EDM machining utilizes quickly recurring current discharges between two electrodes to remove excess material from the workpiece. During the EDM process, the tool and workpiece will not make physical contact. CNC machines and equipment allow the use of some new electrical discharge machining techniques. EDM machining is commonly used in the die and mold-making industry and can be used to machine hard materials and..."
    },
    {
      "hash": "08a5cd6a883b66afd72ab9d1c6d1068efcadeb8a",
      "heading": "Why Use EDM Machining?",
      "level": "h2",
      "text": "Why Use EDM Machining? In some industries, many special parts and products may have high requirements, as a high-precision manufacturing process, the EDM machining process can machine difficult materials and complex parts precisely, and can work to very tight tolerances, such as +/- 0.012mm, which makes it become important in lots of manufacturing fields, especially critical industries like aerospace and medical. Advantages of Electrical Discharge Machining – Not affected by heat during the process. – The hardness of tools doesn’t need to be higher than that of materials. – Can be applied to any electrically conductive materials. – High complexity, high accuracy, and good surface finish can..."
    },
    {
      "hash": "08a5cd6a883b66afd72ab9d1c6d1068efcadeb8a",
      "heading": "Advantages of Electrical Discharge Machining",
      "level": "h3",
      "text": "Why Use EDM Machining? In some industries, many special parts and products may have high requirements, as a high-precision manufacturing process, the EDM machining process can machine difficult materials and complex parts precisely, and can work to very tight tolerances, such as +/- 0.012mm, which makes it become important in lots of manufacturing fields, especially critical industries like aerospace and medical. Advantages of Electrical Discharge Machining – Not affected by heat during the process. – The hardness of tools doesn’t need to be higher than that of materials. – Can be applied to any electrically conductive materials. – High complexity, high accuracy, and good surface finish can..."
    },
    {
      "hash": "10775fb91a7f5c79289f038a8b916e302e840a0a",
      "heading": "EDM Services – Top-Notch Electrical Discharge Machining Services",
      "level": "h2",
      "text": "EDM Services – Top-Notch Electrical Discharge Machining Services At Junying, our EDM services provide multiple types of precision EDM machining to manufacture custom EDM parts with high accuracy, as a top-notch EDM engineering and EDM service supplier, we can also provide design services, high-precision prototypes, as well as electrical discharge machining parts for medium to high-volume runes. Welcome to contact us to get a fast, free online quote for your orders. The following EDM machining services are provided here. CNC Wire EDM Die Sinking EDM EDM Hole Drilling EDM Hole Popping"
    },
    {
      "hash": "e3ddfa3db8964fafd92c460d9a9b1ff641477913",
      "heading": "Types of EDM Machining",
      "level": "h2",
      "text": "Types of EDM Machining Common types of electrical discharge machining include wire EDM, die-sinking EDM, and hole-drilling EDM. Wire EDM Wire EDM , which is also known as wire-cut EDM, wire cutting, wire erosion, and more, uses a CNC-controlled thin electrode wire to cut metal workpieces, the wire is charged to the desired voltage and surrounded by deionized water, it does not contact the workpiece directly when the voltage achieves at a certain level, sparks form between the wire and workpiece will melt the part surface. Wire EDM uses the same mechanism as die-sinking EDM but applies an electrically charged wire instead of the die to act as the electrode. The wire used in wire EMD usually..."
    },
    {
      "hash": "a2acb19c98ab59d6ff5ce91732a0f01ea014f171",
      "heading": "Advantages of Wire EDM",
      "level": "h3",
      "text": "Advantages of Wire EDM – Since the electrode of wire EDM is 0.03-0.35mm metal wire, there is no need to process a particular electrode, which saves time and considerably improves productivity. – Wire EDM products are unaffected by the hardness of the material and are capable of processing conductive materials that cannot be created by other methods. – Materials may be chopped after heat treatment to eliminate deformation issues produced by the post-heat treatment. – In addition to the influence of wire and gap at the product’s inner corner, WEDM may make virtually any shape of the product. – WEDM has unrivaled advantages over other forms of machining for milling precious metals. It increase..."
    },
    {
      "hash": "47286f04a54b88dac77ab54f1b4d0e9d29c48541",
      "heading": "Advantages of Die Sinking EDM",
      "level": "h3",
      "text": "Die sinking EDM is usually used to process conductive materials, the electrode material used in sinker EDM can transfer the electric pulses to the surface of the parts for spark erosion but with minimum erosion of the electrode, common electrodes are copper, brass, graphite, tungsten, carbides, copper-graphite, etc. Advantages of Die Sinking EDM – Sinker EDM is able to produce complex shapes and parts that are difficult to produce with conventional tools. – Delicate details and fragile materials can be machined without distortion, as the tool does not directly contact the workpiece. – Good surface finish can be achieved using die-sinking EDM as the movements are restricted by axes. – The op..."
    },
    {
      "hash": "bd42586eb9edaa2eed2808539ee51542d391b690",
      "heading": "Advantages of Hole-Drilling EDM",
      "level": "h3",
      "text": "Hole-drilling electrical discharge machining is a unique and quick way to produce small and deep holes accurately in conductive materials and does not need deburring which may occur in traditional drilling methods. Hole-drilling methods apply the same principles as die-sinking EDM, but the cut is completed by a pulsing cylindrical electrode, and dielectric fluid is fed into the cutting area and moved deeper into the workpiece. Hole-drilling EDM has advantages in the manufacturing of high-temperature turbine blades, it can create intricate cooling channels inside the blades. Advantages of Hole-Drilling EDM – EDM drilling machines do not rely on physical force to use the tool and can work wit..."
    },
    {
      "hash": "a0d94e7c8ea475dfbc92e1e33c78c390c6bc8775",
      "heading": "EDM Machining Materials – What Materials Can Be Machined by EDM",
      "level": "h2",
      "text": "EDM Machining Materials – What Materials Can Be Machined by EDM EDM is a typical non-traditional machining method, the local and instantaneous high temperature generated by the pulse spark discharge between the two electrodes can cause the materials to be eroded due to melting splash or vaporization. There is no direct mechanical contact during the processing, and it is not limited by the mechanical properties of materials. It is suitable for machining some conductive materials with high hardness, high strength, and high brittleness. In a summary, almost all conductive materials can be processed with electrical discharge machining. Here are some typical choices: Brass Copper Aluminum Tianiu..."
    },
    {
      "hash": "a6c869186e2a2a7350ceb4ac0bf96115c3e3b164",
      "heading": "Applications of Electrical Discharge Machining",
      "level": "h2",
      "text": "Applications of Electrical Discharge Machining EDM machining is widely used in machinery, mold making, aerospace, electronics, aviation, precision machinery, instrumentation, automobile, tractor, light industry, and other industries. It is used to solve the production problems of difficult-to-machine materials and complex shapes. The machining ranges from small shafts, holes, and seams of several microns to super large molds and parts of several meters. – Wire cutting – Threat cutting – Rotary form cutting – Micro-hole drilling – Curved-hole drilling – Hard-material engraving – Helical profile milling – Injection molding – Die casting"
    },
    {
      "hash": "1430772a9bbf30a2c25589c62663bc8f41fc2256",
      "heading": "When to Use EDM – When EDM Machining is Needed?",
      "level": "h2",
      "text": "When to Use EDM – When EDM Machining is Needed? Although EDM machining has various advantages, when should you use it instead of other processes? There are some applications that you can consider for electric discharge machining first. Machining hard materials When you need to work with hard metals like titanium and other difficult-to-machine materials, EDM is preferred as it can easily remove materials on the workpiece without damage. Creating complex or uncommon shapes EDM machining can fabricate complex shapes that are difficult or impossible to machine with conventional machining, and uncommon features like sharp corners and bending holes also can leave a good surface finish and high ac..."
    },
    {
      "hash": "6b393a0bcfd96862d9e997e9aaef91c46b7d5409",
      "heading": "Die Sinking EDM vs Wire EDM, What’s the Difference and Which One to Choose?",
      "level": "h2",
      "text": "Die Sinking EDM vs Wire EDM, What’s the Difference and Which One to Choose? Die sinking EDM and wire EDM are two common types of electric discharge machining, they are both machining processes that utilize thermal energy with some similarities, but there are also lots of differences between them. 1.Tool electrode Die sinking EDM uses a die made of conductive metal as the tool electrode, while the wire EDM applies a conductive wire as the electrode. 2.Complexity Sinker EDM can produce intricate shapes with high precision and accuracy, with a complex die cavity, while wire EDM is typically used for creating more straightforward shapes or 2D cuts. 3.Starting point Die-sinking electric discharg..."
    }
  ],
  "status": 200,
  "structure_hash": "f84abc31a41b62954eb516cfc91e857bad3da409",
  "text_excerpt": "EDM Services & Precision EDM Machining Parts - What is Electrical Discharge Machining Process | Junying [email protected] +86 769 8289 0830 Design Calculator Turning Speed And Feed Calculator Drilling Speed And Feed Calculator Milling Speed And Feed Calculator CNC Programming Services Products About Us Get a Quote Services Machining techniques 5 Axis Machining CNC Turning CNC Milling Swiss Machining CNC Machining Services 3D Printing Rapid prototyping Precision Machining sheet metal fabrication Cooperative supply services EDM Machining Investment Casting Aluminum Extrusion Forging Services Materials CNC Metal Machining CNC Machining Brass CNC Machining Copper CNC Machining Aluminum CNC Machining Titanium CNC Machining Steel CNC Machining Stainless Steel CNC Plastic Machining CNC Machining ABS CNC Machining Nylon CNC Machining POM CNC Machining PEEK CNC Machining PMMA CNC Machining PTFE CNC Machining Polystyrene CNC Machining Polyethylene CNC Machining Polycarbonate Sheet Metal Fabrication Aluminum Sheet Metal Fabrication Brass Sheet Metal Fabrication Copper Sheet Metal Fabrication Steel Sheet Metal Fabrication Stainless Steel Sheet Metal Fabrication Finishing Guide Contact Us Gene...",
  "text_hash": "2ab809f8c92e5c69426e4deeea7ccfef97dd5843",
  "title": "EDM Services & Precision EDM Machining Parts - What is Electrical Discharge Machining Process | Junying",
  "url": "https://www.cnclathing.com/edm-machining"
}