{
  "canonical": "https://jlccnc.com/blog/depth-of-cut",
  "category": "content",
  "competitor": "JLC CNC",
  "ctas": [
    {
      "href": "https://jlccnc.com/help/contact/CNC%20Inquiry",
      "text": "Email Us>"
    },
    {
      "href": "https://jlccnc.com/cnc-machining-quote",
      "text": "Order Now"
    },
    {
      "href": "/blog/category/industry-use-cases",
      "text": "Industry Use Cases"
    },
    {
      "href": "https://jlccnc.com/cnc-machining-quote?from=josie",
      "text": "Get Instant Quote"
    },
    {
      "href": "https://jlccnc.com/help/contact",
      "text": "Email Us >"
    },
    {
      "href": "https://jlccnc.com/help/article/how-to-place-cnc-orders",
      "text": "How To Order"
    },
    {
      "href": "https://jlccnc.com/help/article/How-to-track-my-order",
      "text": "How to Track"
    },
    {
      "href": "https://jlccnc.com/help/article/How-to-submit-the-CNC-order-Complaint",
      "text": "After-Sales Service"
    },
    {
      "href": "https://jlccnc.com/help/contact",
      "text": "Contact Us"
    }
  ],
  "fetched_at": "2026-07-15T04:26:10+00:00",
  "h1": "Depth of Cut in CNC Machining: Definition, Calculation, and Process Optimization",
  "headings": [
    {
      "level": "h1",
      "text": "Depth of Cut in CNC Machining: Definition, Calculation, and Process Optimization"
    },
    {
      "level": "h3",
      "text": "Key Takeaways About Depth of Cut"
    },
    {
      "level": "h2",
      "text": "What Is Depth of Cut in CNC Machining?"
    },
    {
      "level": "h3",
      "text": "How It Is Measured"
    },
    {
      "level": "h3",
      "text": "Difference From Cutting Width (Stepover)"
    },
    {
      "level": "h2",
      "text": "Axial Cutting vs Radial Cutting"
    },
    {
      "level": "h3",
      "text": "What Is Axial Depth of Cut (Ap)"
    },
    {
      "level": "h3",
      "text": "What Is Radial Depth of Cut (Ae)"
    },
    {
      "level": "h3",
      "text": "How Axial and Radial Engagement Work Together"
    },
    {
      "level": "h2",
      "text": "Why Depth of Cut Matters in CNC Machining"
    },
    {
      "level": "h3",
      "text": "Material Removal Rate and Productivity"
    },
    {
      "level": "h3",
      "text": "Cutting Forces and Machine Load"
    },
    {
      "level": "h3",
      "text": "Tool Life and Wear"
    },
    {
      "level": "h3",
      "text": "Surface Finish and Dimensional Accuracy"
    },
    {
      "level": "h2",
      "text": "How Depth of Cut Is Determined"
    },
    {
      "level": "h3",
      "text": "Workpiece Material Properties"
    },
    {
      "level": "h3",
      "text": "Tool Diameter and Tool Geometry"
    },
    {
      "level": "h3",
      "text": "Machine Rigidity and Available Power"
    },
    {
      "level": "h3",
      "text": "Workholding Stability"
    },
    {
      "level": "h3",
      "text": "Balancing DOC With Feed Rate and Cutting Speed"
    },
    {
      "level": "h2",
      "text": "How to Calculate Depth of Cut"
    },
    {
      "level": "h3",
      "text": "Milling Calculation"
    },
    {
      "level": "h3",
      "text": "Lathe Calculation"
    },
    {
      "level": "h3",
      "text": "Link to Material Removal Rate"
    },
    {
      "level": "h2",
      "text": "Depth of Cut in Different Machining Operations"
    },
    {
      "level": "h3",
      "text": "Face Milling"
    },
    {
      "level": "h3",
      "text": "End Milling"
    },
    {
      "level": "h3",
      "text": "Slot Milling"
    },
    {
      "level": "h3",
      "text": "CNC Lathe Operations"
    },
    {
      "level": "h2",
      "text": "End Mill Depth of Cut Guidelines"
    },
    {
      "level": "h3",
      "text": "Common Rule-of-Thumb Recommendations"
    },
    {
      "level": "h3",
      "text": "Why Tool Diameter Matters"
    },
    {
      "level": "h3",
      "text": "Full-Width vs Light Radial Engagement"
    },
    {
      "level": "h3",
      "text": "When Recommended Values Should Be Adjusted"
    },
    {
      "level": "h3",
      "text": "Validating Parameters Through Test Cuts"
    },
    {
      "level": "h2",
      "text": "Typical Depth of Cut Ranges by Material"
    },
    {
      "level": "h3",
      "text": "Precision CNC Machining Service"
    },
    {
      "level": "h2",
      "text": "Depth of Cut and Machining Strategy"
    },
    {
      "level": "h3",
      "text": "Roughing for Maximum Material Removal"
    },
    {
      "level": "h3",
      "text": "Semi-Finishing Operations"
    },
    {
      "level": "h3",
      "text": "Finishing Passes for Surface Quality"
    },
    {
      "level": "h3",
      "text": "High-Efficiency Machining Strategies"
    },
    {
      "level": "h2",
      "text": "Common Problems Caused by Incorrect Depth of Cut"
    },
    {
      "level": "h3",
      "text": "Excessive Tool Deflection"
    },
    {
      "level": "h3",
      "text": "Chatter and Vibration"
    },
    {
      "level": "h3",
      "text": "Premature Tool Wear"
    },
    {
      "level": "h3",
      "text": "Low Productivity and Excessive Cycle Time"
    },
    {
      "level": "h2",
      "text": "Depth of Cut vs Other Cutting Parameters"
    },
    {
      "level": "h3",
      "text": "Depth of Cut vs Feed Rate"
    },
    {
      "level": "h3",
      "text": "Compared With Cutting Speed"
    },
    {
      "level": "h3",
      "text": "Compared With Stepover"
    },
    {
      "level": "h3",
      "text": "Compared With Chip Load"
    },
    {
      "level": "h2",
      "text": "Conclusion About Depth of Cut"
    },
    {
      "level": "h3",
      "text": "Precision CNC Machining Service"
    },
    {
      "level": "h2",
      "text": "FAQ About Depth of Cut"
    },
    {
      "level": "h3",
      "text": "Q: What is the depth of cut in CNC machining?"
    },
    {
      "level": "h3",
      "text": "Q: What is the maximum depth of cut for an end mill?"
    },
    {
      "level": "h3",
      "text": "Q: What is axial cutting?"
    },
    {
      "level": "h3",
      "text": "Q: What is the difference between axial and radial depth of cut?"
    },
    {
      "level": "h3",
      "text": "Q: How does depth of cut affect tool life?"
    },
    {
      "level": "h3",
      "text": "Q: What is a typical end mill depth of cut?"
    },
    {
      "level": "h3",
      "text": "Q: Does increasing depth of cut always improve productivity?"
    },
    {
      "level": "h3",
      "text": "Q: How is the depth of cut different from stepover?"
    },
    {
      "level": "h3",
      "text": "Q: How do machinists determine the correct depth of cut?"
    },
    {
      "level": "h3",
      "text": "Q: Are different cut depths used for roughing and finishing?"
    }
  ],
  "images": [
    {
      "alt": "jlccnc navigation cnc machining service cnc machining",
      "src": "https://rs.jlccnc.com/static/image/homepage/navigation-cnc-machining-service-cnc-milling.webp"
    },
    {
      "alt": "jlccnc navigation cnc machining service cnc milling",
      "src": "https://rs.jlccnc.com/static/image/homepage/navigation-cnc-machining-service-cnc-machining.webp"
    },
    {
      "alt": "jlccnc navigation cnc machining service cnc turning",
      "src": "https://rs.jlccnc.com/static/image/homepage/navigation-cnc-machining-service-cnc-turning.webp"
    },
    {
      "alt": "jlccnc navigation cnc machining service edm",
      "src": "https://rs.jlccnc.com/static/image/homepage/navigation-cnc-machining-service-edm.webp"
    },
    {
      "alt": "jlccnc navigation cnc machining service sheet metal",
      "src": "https://rs.jlccnc.com/static/image/homepage/navigation-cnc-machining-service-sheet-metal.webp"
    },
    {
      "alt": "CNC milling tool showing depth of cut on metal part",
      "src": "https://rs.jlccnc.com/static/image/blog/Knowledge-Hub/CNC-Machining-Fundamentals/CNC-milling-tool-showing-depth-of-cut-on-metal-part.jpg"
    },
    {
      "alt": "Axial and radial depth of cut in CNC milling",
      "src": "https://rs.jlccnc.com/static/image/blog/Knowledge-Hub/CNC-Machining-Fundamentals/Axial-and-radial-depth-of-cut-in-CNC-milling.jpg"
    },
    {
      "alt": "CNC depth of cut across milling and turning operations",
      "src": "https://rs.jlccnc.com/static/image/blog/Knowledge-Hub/CNC-Machining-Fundamentals/CNC-depth-of-cut-across-milling-and-turning-operations.jpg"
    },
    {
      "alt": "JLCCNC Logo",
      "src": "https://rs.jlccnc.com/static/image/blog/banner/CNC-logo%E9%80%8F%E6%98%8E%E5%BA%95.png"
    },
    {
      "alt": "CNC depth of cut with feed, speed, stepover, chip load",
      "src": "https://rs.jlccnc.com/static/image/blog/Knowledge-Hub/CNC-Machining-Fundamentals/CNC-depth-of-cut-with-feed%2C-speed%2C-stepover%2C-chip-load.jpg"
    }
  ],
  "meta_description": "Learn what depth of cut means in CNC machining, how to calculate axial and radial engagement, and how to optimize tool life, finish, and productivity.",
  "requested_url": "https://jlccnc.com/blog/depth-of-cut",
  "sections": [
    {
      "hash": "79332d84dfc88cb4234a9568c87586e5e55b9f8a",
      "heading": "Depth of Cut in CNC Machining: Definition, Calculation, and Process Optimization",
      "level": "h1",
      "text": "Depth of Cut in CNC Machining: Definition, Calculation, and Process Optimization Published Jun 12, 2026, updated Jun 12, 2026 13 min Table of Contents What Is Depth of Cut in CNC Machining? Axial Cutting vs Radial Cutting Why Depth of Cut Matters in CNC Machining How Depth of Cut Is Determined How to Calculate Depth of Cut Depth of Cut in Different Machining Operations End Mill Depth of Cut Guidelines Typical Depth of Cut Ranges by Material Depth of Cut and Machining Strategy Common Problems Caused by Incorrect Depth of Cut Depth of Cut vs Other Cutting Parameters Conclusion About Depth of Cut FAQ About Depth of Cut Key Takeaways About Depth of Cut Depth of cut defines how much material a t..."
    },
    {
      "hash": "d2db44e068a185c71f64602c2b65a7aa7f543a18",
      "heading": "Key Takeaways About Depth of Cut",
      "level": "h3",
      "text": "Key Takeaways About Depth of Cut Depth of cut defines how much material a tool removes per pass and sets the pace for machining operations. Axial and radial engagement interact to determine cutter contact, influencing tool load and part accuracy. Material hardness, wall thickness, and feature geometry affect how aggressively a cut can be applied. Cutting too deep or too shallow can cause tool wear, surface marks, or extended cycle time. Test cuts and CAD review help verify depth of cut for each part before full production."
    },
    {
      "hash": "ff238fc21a401e13880dbb5145da27eeb744ebb8",
      "heading": "What Is Depth of Cut in CNC Machining?",
      "level": "h2",
      "text": "Key Takeaways About Depth of Cut Depth of cut defines how much material a tool removes per pass and sets the pace for machining operations. Axial and radial engagement interact to determine cutter contact, influencing tool load and part accuracy. Material hardness, wall thickness, and feature geometry affect how aggressively a cut can be applied. Cutting too deep or too shallow can cause tool wear, surface marks, or extended cycle time. Test cuts and CAD review help verify depth of cut for each part before full production. CNC milling tool showing depth of cut on metal part In CNC machining, depth of cut is one of those choices that guides the entire job. Excessive depth of cut can cause pr..."
    },
    {
      "hash": "ff238fc21a401e13880dbb5145da27eeb744ebb8",
      "heading": "How It Is Measured",
      "level": "h3",
      "text": "Key Takeaways About Depth of Cut Depth of cut defines how much material a tool removes per pass and sets the pace for machining operations. Axial and radial engagement interact to determine cutter contact, influencing tool load and part accuracy. Material hardness, wall thickness, and feature geometry affect how aggressively a cut can be applied. Cutting too deep or too shallow can cause tool wear, surface marks, or extended cycle time. Test cuts and CAD review help verify depth of cut for each part before full production. CNC milling tool showing depth of cut on metal part In CNC machining, depth of cut is one of those choices that guides the entire job. Excessive depth of cut can cause pr..."
    },
    {
      "hash": "ff238fc21a401e13880dbb5145da27eeb744ebb8",
      "heading": "Difference From Cutting Width (Stepover)",
      "level": "h3",
      "text": "Key Takeaways About Depth of Cut Depth of cut defines how much material a tool removes per pass and sets the pace for machining operations. Axial and radial engagement interact to determine cutter contact, influencing tool load and part accuracy. Material hardness, wall thickness, and feature geometry affect how aggressively a cut can be applied. Cutting too deep or too shallow can cause tool wear, surface marks, or extended cycle time. Test cuts and CAD review help verify depth of cut for each part before full production. CNC milling tool showing depth of cut on metal part In CNC machining, depth of cut is one of those choices that guides the entire job. Excessive depth of cut can cause pr..."
    },
    {
      "hash": "ff238fc21a401e13880dbb5145da27eeb744ebb8",
      "heading": "Axial Cutting vs Radial Cutting",
      "level": "h2",
      "text": "Key Takeaways About Depth of Cut Depth of cut defines how much material a tool removes per pass and sets the pace for machining operations. Axial and radial engagement interact to determine cutter contact, influencing tool load and part accuracy. Material hardness, wall thickness, and feature geometry affect how aggressively a cut can be applied. Cutting too deep or too shallow can cause tool wear, surface marks, or extended cycle time. Test cuts and CAD review help verify depth of cut for each part before full production. CNC milling tool showing depth of cut on metal part In CNC machining, depth of cut is one of those choices that guides the entire job. Excessive depth of cut can cause pr..."
    },
    {
      "hash": "ff238fc21a401e13880dbb5145da27eeb744ebb8",
      "heading": "What Is Axial Depth of Cut (Ap)",
      "level": "h3",
      "text": "Key Takeaways About Depth of Cut Depth of cut defines how much material a tool removes per pass and sets the pace for machining operations. Axial and radial engagement interact to determine cutter contact, influencing tool load and part accuracy. Material hardness, wall thickness, and feature geometry affect how aggressively a cut can be applied. Cutting too deep or too shallow can cause tool wear, surface marks, or extended cycle time. Test cuts and CAD review help verify depth of cut for each part before full production. CNC milling tool showing depth of cut on metal part In CNC machining, depth of cut is one of those choices that guides the entire job. Excessive depth of cut can cause pr..."
    },
    {
      "hash": "ff238fc21a401e13880dbb5145da27eeb744ebb8",
      "heading": "What Is Radial Depth of Cut (Ae)",
      "level": "h3",
      "text": "Key Takeaways About Depth of Cut Depth of cut defines how much material a tool removes per pass and sets the pace for machining operations. Axial and radial engagement interact to determine cutter contact, influencing tool load and part accuracy. Material hardness, wall thickness, and feature geometry affect how aggressively a cut can be applied. Cutting too deep or too shallow can cause tool wear, surface marks, or extended cycle time. Test cuts and CAD review help verify depth of cut for each part before full production. CNC milling tool showing depth of cut on metal part In CNC machining, depth of cut is one of those choices that guides the entire job. Excessive depth of cut can cause pr..."
    },
    {
      "hash": "ff238fc21a401e13880dbb5145da27eeb744ebb8",
      "heading": "How Axial and Radial Engagement Work Together",
      "level": "h3",
      "text": "Key Takeaways About Depth of Cut Depth of cut defines how much material a tool removes per pass and sets the pace for machining operations. Axial and radial engagement interact to determine cutter contact, influencing tool load and part accuracy. Material hardness, wall thickness, and feature geometry affect how aggressively a cut can be applied. Cutting too deep or too shallow can cause tool wear, surface marks, or extended cycle time. Test cuts and CAD review help verify depth of cut for each part before full production. CNC milling tool showing depth of cut on metal part In CNC machining, depth of cut is one of those choices that guides the entire job. Excessive depth of cut can cause pr..."
    },
    {
      "hash": "ff238fc21a401e13880dbb5145da27eeb744ebb8",
      "heading": "Why Depth of Cut Matters in CNC Machining",
      "level": "h2",
      "text": "Key Takeaways About Depth of Cut Depth of cut defines how much material a tool removes per pass and sets the pace for machining operations. Axial and radial engagement interact to determine cutter contact, influencing tool load and part accuracy. Material hardness, wall thickness, and feature geometry affect how aggressively a cut can be applied. Cutting too deep or too shallow can cause tool wear, surface marks, or extended cycle time. Test cuts and CAD review help verify depth of cut for each part before full production. CNC milling tool showing depth of cut on metal part In CNC machining, depth of cut is one of those choices that guides the entire job. Excessive depth of cut can cause pr..."
    },
    {
      "hash": "ff238fc21a401e13880dbb5145da27eeb744ebb8",
      "heading": "Material Removal Rate and Productivity",
      "level": "h3",
      "text": "Key Takeaways About Depth of Cut Depth of cut defines how much material a tool removes per pass and sets the pace for machining operations. Axial and radial engagement interact to determine cutter contact, influencing tool load and part accuracy. Material hardness, wall thickness, and feature geometry affect how aggressively a cut can be applied. Cutting too deep or too shallow can cause tool wear, surface marks, or extended cycle time. Test cuts and CAD review help verify depth of cut for each part before full production. CNC milling tool showing depth of cut on metal part In CNC machining, depth of cut is one of those choices that guides the entire job. Excessive depth of cut can cause pr..."
    },
    {
      "hash": "ff238fc21a401e13880dbb5145da27eeb744ebb8",
      "heading": "Cutting Forces and Machine Load",
      "level": "h3",
      "text": "Key Takeaways About Depth of Cut Depth of cut defines how much material a tool removes per pass and sets the pace for machining operations. Axial and radial engagement interact to determine cutter contact, influencing tool load and part accuracy. Material hardness, wall thickness, and feature geometry affect how aggressively a cut can be applied. Cutting too deep or too shallow can cause tool wear, surface marks, or extended cycle time. Test cuts and CAD review help verify depth of cut for each part before full production. CNC milling tool showing depth of cut on metal part In CNC machining, depth of cut is one of those choices that guides the entire job. Excessive depth of cut can cause pr..."
    },
    {
      "hash": "ff238fc21a401e13880dbb5145da27eeb744ebb8",
      "heading": "Tool Life and Wear",
      "level": "h3",
      "text": "Key Takeaways About Depth of Cut Depth of cut defines how much material a tool removes per pass and sets the pace for machining operations. Axial and radial engagement interact to determine cutter contact, influencing tool load and part accuracy. Material hardness, wall thickness, and feature geometry affect how aggressively a cut can be applied. Cutting too deep or too shallow can cause tool wear, surface marks, or extended cycle time. Test cuts and CAD review help verify depth of cut for each part before full production. CNC milling tool showing depth of cut on metal part In CNC machining, depth of cut is one of those choices that guides the entire job. Excessive depth of cut can cause pr..."
    },
    {
      "hash": "ff238fc21a401e13880dbb5145da27eeb744ebb8",
      "heading": "Surface Finish and Dimensional Accuracy",
      "level": "h3",
      "text": "Key Takeaways About Depth of Cut Depth of cut defines how much material a tool removes per pass and sets the pace for machining operations. Axial and radial engagement interact to determine cutter contact, influencing tool load and part accuracy. Material hardness, wall thickness, and feature geometry affect how aggressively a cut can be applied. Cutting too deep or too shallow can cause tool wear, surface marks, or extended cycle time. Test cuts and CAD review help verify depth of cut for each part before full production. CNC milling tool showing depth of cut on metal part In CNC machining, depth of cut is one of those choices that guides the entire job. Excessive depth of cut can cause pr..."
    },
    {
      "hash": "ff238fc21a401e13880dbb5145da27eeb744ebb8",
      "heading": "How Depth of Cut Is Determined",
      "level": "h2",
      "text": "Key Takeaways About Depth of Cut Depth of cut defines how much material a tool removes per pass and sets the pace for machining operations. Axial and radial engagement interact to determine cutter contact, influencing tool load and part accuracy. Material hardness, wall thickness, and feature geometry affect how aggressively a cut can be applied. Cutting too deep or too shallow can cause tool wear, surface marks, or extended cycle time. Test cuts and CAD review help verify depth of cut for each part before full production. CNC milling tool showing depth of cut on metal part In CNC machining, depth of cut is one of those choices that guides the entire job. Excessive depth of cut can cause pr..."
    },
    {
      "hash": "ff238fc21a401e13880dbb5145da27eeb744ebb8",
      "heading": "Workpiece Material Properties",
      "level": "h3",
      "text": "Key Takeaways About Depth of Cut Depth of cut defines how much material a tool removes per pass and sets the pace for machining operations. Axial and radial engagement interact to determine cutter contact, influencing tool load and part accuracy. Material hardness, wall thickness, and feature geometry affect how aggressively a cut can be applied. Cutting too deep or too shallow can cause tool wear, surface marks, or extended cycle time. Test cuts and CAD review help verify depth of cut for each part before full production. CNC milling tool showing depth of cut on metal part In CNC machining, depth of cut is one of those choices that guides the entire job. Excessive depth of cut can cause pr..."
    },
    {
      "hash": "ff238fc21a401e13880dbb5145da27eeb744ebb8",
      "heading": "Tool Diameter and Tool Geometry",
      "level": "h3",
      "text": "Key Takeaways About Depth of Cut Depth of cut defines how much material a tool removes per pass and sets the pace for machining operations. Axial and radial engagement interact to determine cutter contact, influencing tool load and part accuracy. Material hardness, wall thickness, and feature geometry affect how aggressively a cut can be applied. Cutting too deep or too shallow can cause tool wear, surface marks, or extended cycle time. Test cuts and CAD review help verify depth of cut for each part before full production. CNC milling tool showing depth of cut on metal part In CNC machining, depth of cut is one of those choices that guides the entire job. Excessive depth of cut can cause pr..."
    },
    {
      "hash": "ff238fc21a401e13880dbb5145da27eeb744ebb8",
      "heading": "Machine Rigidity and Available Power",
      "level": "h3",
      "text": "Key Takeaways About Depth of Cut Depth of cut defines how much material a tool removes per pass and sets the pace for machining operations. Axial and radial engagement interact to determine cutter contact, influencing tool load and part accuracy. Material hardness, wall thickness, and feature geometry affect how aggressively a cut can be applied. Cutting too deep or too shallow can cause tool wear, surface marks, or extended cycle time. Test cuts and CAD review help verify depth of cut for each part before full production. CNC milling tool showing depth of cut on metal part In CNC machining, depth of cut is one of those choices that guides the entire job. Excessive depth of cut can cause pr..."
    },
    {
      "hash": "ff238fc21a401e13880dbb5145da27eeb744ebb8",
      "heading": "Workholding Stability",
      "level": "h3",
      "text": "Key Takeaways About Depth of Cut Depth of cut defines how much material a tool removes per pass and sets the pace for machining operations. Axial and radial engagement interact to determine cutter contact, influencing tool load and part accuracy. Material hardness, wall thickness, and feature geometry affect how aggressively a cut can be applied. Cutting too deep or too shallow can cause tool wear, surface marks, or extended cycle time. Test cuts and CAD review help verify depth of cut for each part before full production. CNC milling tool showing depth of cut on metal part In CNC machining, depth of cut is one of those choices that guides the entire job. Excessive depth of cut can cause pr..."
    },
    {
      "hash": "ff238fc21a401e13880dbb5145da27eeb744ebb8",
      "heading": "Balancing DOC With Feed Rate and Cutting Speed",
      "level": "h3",
      "text": "Key Takeaways About Depth of Cut Depth of cut defines how much material a tool removes per pass and sets the pace for machining operations. Axial and radial engagement interact to determine cutter contact, influencing tool load and part accuracy. Material hardness, wall thickness, and feature geometry affect how aggressively a cut can be applied. Cutting too deep or too shallow can cause tool wear, surface marks, or extended cycle time. Test cuts and CAD review help verify depth of cut for each part before full production. CNC milling tool showing depth of cut on metal part In CNC machining, depth of cut is one of those choices that guides the entire job. Excessive depth of cut can cause pr..."
    },
    {
      "hash": "ff238fc21a401e13880dbb5145da27eeb744ebb8",
      "heading": "How to Calculate Depth of Cut",
      "level": "h2",
      "text": "Key Takeaways About Depth of Cut Depth of cut defines how much material a tool removes per pass and sets the pace for machining operations. Axial and radial engagement interact to determine cutter contact, influencing tool load and part accuracy. Material hardness, wall thickness, and feature geometry affect how aggressively a cut can be applied. Cutting too deep or too shallow can cause tool wear, surface marks, or extended cycle time. Test cuts and CAD review help verify depth of cut for each part before full production. CNC milling tool showing depth of cut on metal part In CNC machining, depth of cut is one of those choices that guides the entire job. Excessive depth of cut can cause pr..."
    },
    {
      "hash": "ff238fc21a401e13880dbb5145da27eeb744ebb8",
      "heading": "Milling Calculation",
      "level": "h3",
      "text": "Key Takeaways About Depth of Cut Depth of cut defines how much material a tool removes per pass and sets the pace for machining operations. Axial and radial engagement interact to determine cutter contact, influencing tool load and part accuracy. Material hardness, wall thickness, and feature geometry affect how aggressively a cut can be applied. Cutting too deep or too shallow can cause tool wear, surface marks, or extended cycle time. Test cuts and CAD review help verify depth of cut for each part before full production. CNC milling tool showing depth of cut on metal part In CNC machining, depth of cut is one of those choices that guides the entire job. Excessive depth of cut can cause pr..."
    },
    {
      "hash": "ff238fc21a401e13880dbb5145da27eeb744ebb8",
      "heading": "Lathe Calculation",
      "level": "h3",
      "text": "Key Takeaways About Depth of Cut Depth of cut defines how much material a tool removes per pass and sets the pace for machining operations. Axial and radial engagement interact to determine cutter contact, influencing tool load and part accuracy. Material hardness, wall thickness, and feature geometry affect how aggressively a cut can be applied. Cutting too deep or too shallow can cause tool wear, surface marks, or extended cycle time. Test cuts and CAD review help verify depth of cut for each part before full production. CNC milling tool showing depth of cut on metal part In CNC machining, depth of cut is one of those choices that guides the entire job. Excessive depth of cut can cause pr..."
    },
    {
      "hash": "ff238fc21a401e13880dbb5145da27eeb744ebb8",
      "heading": "Link to Material Removal Rate",
      "level": "h3",
      "text": "Key Takeaways About Depth of Cut Depth of cut defines how much material a tool removes per pass and sets the pace for machining operations. Axial and radial engagement interact to determine cutter contact, influencing tool load and part accuracy. Material hardness, wall thickness, and feature geometry affect how aggressively a cut can be applied. Cutting too deep or too shallow can cause tool wear, surface marks, or extended cycle time. Test cuts and CAD review help verify depth of cut for each part before full production. CNC milling tool showing depth of cut on metal part In CNC machining, depth of cut is one of those choices that guides the entire job. Excessive depth of cut can cause pr..."
    },
    {
      "hash": "ff238fc21a401e13880dbb5145da27eeb744ebb8",
      "heading": "Depth of Cut in Different Machining Operations",
      "level": "h2",
      "text": "Key Takeaways About Depth of Cut Depth of cut defines how much material a tool removes per pass and sets the pace for machining operations. Axial and radial engagement interact to determine cutter contact, influencing tool load and part accuracy. Material hardness, wall thickness, and feature geometry affect how aggressively a cut can be applied. Cutting too deep or too shallow can cause tool wear, surface marks, or extended cycle time. Test cuts and CAD review help verify depth of cut for each part before full production. CNC milling tool showing depth of cut on metal part In CNC machining, depth of cut is one of those choices that guides the entire job. Excessive depth of cut can cause pr..."
    },
    {
      "hash": "ff238fc21a401e13880dbb5145da27eeb744ebb8",
      "heading": "Face Milling",
      "level": "h3",
      "text": "Key Takeaways About Depth of Cut Depth of cut defines how much material a tool removes per pass and sets the pace for machining operations. Axial and radial engagement interact to determine cutter contact, influencing tool load and part accuracy. Material hardness, wall thickness, and feature geometry affect how aggressively a cut can be applied. Cutting too deep or too shallow can cause tool wear, surface marks, or extended cycle time. Test cuts and CAD review help verify depth of cut for each part before full production. CNC milling tool showing depth of cut on metal part In CNC machining, depth of cut is one of those choices that guides the entire job. Excessive depth of cut can cause pr..."
    },
    {
      "hash": "ff238fc21a401e13880dbb5145da27eeb744ebb8",
      "heading": "End Milling",
      "level": "h3",
      "text": "Key Takeaways About Depth of Cut Depth of cut defines how much material a tool removes per pass and sets the pace for machining operations. Axial and radial engagement interact to determine cutter contact, influencing tool load and part accuracy. Material hardness, wall thickness, and feature geometry affect how aggressively a cut can be applied. Cutting too deep or too shallow can cause tool wear, surface marks, or extended cycle time. Test cuts and CAD review help verify depth of cut for each part before full production. CNC milling tool showing depth of cut on metal part In CNC machining, depth of cut is one of those choices that guides the entire job. Excessive depth of cut can cause pr..."
    },
    {
      "hash": "ff238fc21a401e13880dbb5145da27eeb744ebb8",
      "heading": "Slot Milling",
      "level": "h3",
      "text": "Key Takeaways About Depth of Cut Depth of cut defines how much material a tool removes per pass and sets the pace for machining operations. Axial and radial engagement interact to determine cutter contact, influencing tool load and part accuracy. Material hardness, wall thickness, and feature geometry affect how aggressively a cut can be applied. Cutting too deep or too shallow can cause tool wear, surface marks, or extended cycle time. Test cuts and CAD review help verify depth of cut for each part before full production. CNC milling tool showing depth of cut on metal part In CNC machining, depth of cut is one of those choices that guides the entire job. Excessive depth of cut can cause pr..."
    },
    {
      "hash": "ff238fc21a401e13880dbb5145da27eeb744ebb8",
      "heading": "CNC Lathe Operations",
      "level": "h3",
      "text": "Key Takeaways About Depth of Cut Depth of cut defines how much material a tool removes per pass and sets the pace for machining operations. Axial and radial engagement interact to determine cutter contact, influencing tool load and part accuracy. Material hardness, wall thickness, and feature geometry affect how aggressively a cut can be applied. Cutting too deep or too shallow can cause tool wear, surface marks, or extended cycle time. Test cuts and CAD review help verify depth of cut for each part before full production. CNC milling tool showing depth of cut on metal part In CNC machining, depth of cut is one of those choices that guides the entire job. Excessive depth of cut can cause pr..."
    },
    {
      "hash": "ff238fc21a401e13880dbb5145da27eeb744ebb8",
      "heading": "End Mill Depth of Cut Guidelines",
      "level": "h2",
      "text": "Key Takeaways About Depth of Cut Depth of cut defines how much material a tool removes per pass and sets the pace for machining operations. Axial and radial engagement interact to determine cutter contact, influencing tool load and part accuracy. Material hardness, wall thickness, and feature geometry affect how aggressively a cut can be applied. Cutting too deep or too shallow can cause tool wear, surface marks, or extended cycle time. Test cuts and CAD review help verify depth of cut for each part before full production. CNC milling tool showing depth of cut on metal part In CNC machining, depth of cut is one of those choices that guides the entire job. Excessive depth of cut can cause pr..."
    },
    {
      "hash": "ff238fc21a401e13880dbb5145da27eeb744ebb8",
      "heading": "Common Rule-of-Thumb Recommendations",
      "level": "h3",
      "text": "Key Takeaways About Depth of Cut Depth of cut defines how much material a tool removes per pass and sets the pace for machining operations. Axial and radial engagement interact to determine cutter contact, influencing tool load and part accuracy. Material hardness, wall thickness, and feature geometry affect how aggressively a cut can be applied. Cutting too deep or too shallow can cause tool wear, surface marks, or extended cycle time. Test cuts and CAD review help verify depth of cut for each part before full production. CNC milling tool showing depth of cut on metal part In CNC machining, depth of cut is one of those choices that guides the entire job. Excessive depth of cut can cause pr..."
    },
    {
      "hash": "ff238fc21a401e13880dbb5145da27eeb744ebb8",
      "heading": "Why Tool Diameter Matters",
      "level": "h3",
      "text": "Key Takeaways About Depth of Cut Depth of cut defines how much material a tool removes per pass and sets the pace for machining operations. Axial and radial engagement interact to determine cutter contact, influencing tool load and part accuracy. Material hardness, wall thickness, and feature geometry affect how aggressively a cut can be applied. Cutting too deep or too shallow can cause tool wear, surface marks, or extended cycle time. Test cuts and CAD review help verify depth of cut for each part before full production. CNC milling tool showing depth of cut on metal part In CNC machining, depth of cut is one of those choices that guides the entire job. Excessive depth of cut can cause pr..."
    },
    {
      "hash": "ff238fc21a401e13880dbb5145da27eeb744ebb8",
      "heading": "Full-Width vs Light Radial Engagement",
      "level": "h3",
      "text": "Key Takeaways About Depth of Cut Depth of cut defines how much material a tool removes per pass and sets the pace for machining operations. Axial and radial engagement interact to determine cutter contact, influencing tool load and part accuracy. Material hardness, wall thickness, and feature geometry affect how aggressively a cut can be applied. Cutting too deep or too shallow can cause tool wear, surface marks, or extended cycle time. Test cuts and CAD review help verify depth of cut for each part before full production. CNC milling tool showing depth of cut on metal part In CNC machining, depth of cut is one of those choices that guides the entire job. Excessive depth of cut can cause pr..."
    },
    {
      "hash": "ff238fc21a401e13880dbb5145da27eeb744ebb8",
      "heading": "When Recommended Values Should Be Adjusted",
      "level": "h3",
      "text": "Key Takeaways About Depth of Cut Depth of cut defines how much material a tool removes per pass and sets the pace for machining operations. Axial and radial engagement interact to determine cutter contact, influencing tool load and part accuracy. Material hardness, wall thickness, and feature geometry affect how aggressively a cut can be applied. Cutting too deep or too shallow can cause tool wear, surface marks, or extended cycle time. Test cuts and CAD review help verify depth of cut for each part before full production. CNC milling tool showing depth of cut on metal part In CNC machining, depth of cut is one of those choices that guides the entire job. Excessive depth of cut can cause pr..."
    },
    {
      "hash": "ff238fc21a401e13880dbb5145da27eeb744ebb8",
      "heading": "Validating Parameters Through Test Cuts",
      "level": "h3",
      "text": "Key Takeaways About Depth of Cut Depth of cut defines how much material a tool removes per pass and sets the pace for machining operations. Axial and radial engagement interact to determine cutter contact, influencing tool load and part accuracy. Material hardness, wall thickness, and feature geometry affect how aggressively a cut can be applied. Cutting too deep or too shallow can cause tool wear, surface marks, or extended cycle time. Test cuts and CAD review help verify depth of cut for each part before full production. CNC milling tool showing depth of cut on metal part In CNC machining, depth of cut is one of those choices that guides the entire job. Excessive depth of cut can cause pr..."
    },
    {
      "hash": "ff238fc21a401e13880dbb5145da27eeb744ebb8",
      "heading": "Typical Depth of Cut Ranges by Material",
      "level": "h2",
      "text": "Key Takeaways About Depth of Cut Depth of cut defines how much material a tool removes per pass and sets the pace for machining operations. Axial and radial engagement interact to determine cutter contact, influencing tool load and part accuracy. Material hardness, wall thickness, and feature geometry affect how aggressively a cut can be applied. Cutting too deep or too shallow can cause tool wear, surface marks, or extended cycle time. Test cuts and CAD review help verify depth of cut for each part before full production. CNC milling tool showing depth of cut on metal part In CNC machining, depth of cut is one of those choices that guides the entire job. Excessive depth of cut can cause pr..."
    },
    {
      "hash": "8b72fd088458c5d94a532f39f0536099329845b6",
      "heading": "Precision CNC Machining Service",
      "level": "h3",
      "text": "Precision CNC Machining Service"
    },
    {
      "hash": "ff238fc21a401e13880dbb5145da27eeb744ebb8",
      "heading": "Depth of Cut and Machining Strategy",
      "level": "h2",
      "text": "Key Takeaways About Depth of Cut Depth of cut defines how much material a tool removes per pass and sets the pace for machining operations. Axial and radial engagement interact to determine cutter contact, influencing tool load and part accuracy. Material hardness, wall thickness, and feature geometry affect how aggressively a cut can be applied. Cutting too deep or too shallow can cause tool wear, surface marks, or extended cycle time. Test cuts and CAD review help verify depth of cut for each part before full production. CNC milling tool showing depth of cut on metal part In CNC machining, depth of cut is one of those choices that guides the entire job. Excessive depth of cut can cause pr..."
    },
    {
      "hash": "ff238fc21a401e13880dbb5145da27eeb744ebb8",
      "heading": "Roughing for Maximum Material Removal",
      "level": "h3",
      "text": "Key Takeaways About Depth of Cut Depth of cut defines how much material a tool removes per pass and sets the pace for machining operations. Axial and radial engagement interact to determine cutter contact, influencing tool load and part accuracy. Material hardness, wall thickness, and feature geometry affect how aggressively a cut can be applied. Cutting too deep or too shallow can cause tool wear, surface marks, or extended cycle time. Test cuts and CAD review help verify depth of cut for each part before full production. CNC milling tool showing depth of cut on metal part In CNC machining, depth of cut is one of those choices that guides the entire job. Excessive depth of cut can cause pr..."
    },
    {
      "hash": "ff238fc21a401e13880dbb5145da27eeb744ebb8",
      "heading": "Semi-Finishing Operations",
      "level": "h3",
      "text": "Key Takeaways About Depth of Cut Depth of cut defines how much material a tool removes per pass and sets the pace for machining operations. Axial and radial engagement interact to determine cutter contact, influencing tool load and part accuracy. Material hardness, wall thickness, and feature geometry affect how aggressively a cut can be applied. Cutting too deep or too shallow can cause tool wear, surface marks, or extended cycle time. Test cuts and CAD review help verify depth of cut for each part before full production. CNC milling tool showing depth of cut on metal part In CNC machining, depth of cut is one of those choices that guides the entire job. Excessive depth of cut can cause pr..."
    }
  ],
  "status": 200,
  "structure_hash": "a38db16099dbe7e77e8916b58b06056a7f70de35",
  "text_excerpt": "Depth of Cut in CNC Machining: Calculation & Optimization Account Restriction Notice Get Coupon Here Coupons JLCCNC CNC Machining Service CNC Machining CNC Milling CNC Turning EDM Sheet Metal Mechanical Services JLC3DP - 3D Printing JLCMC - Mechatronic Parts Electronics Services PCB Fabrication PCB Assembly SMT Stencil PCB Layout Flex Heater More EasyEDA - CAD Design Tool JLCDFM - DFM Check OSHWLAB - Open Source Hardware 3D Viewer - 3D File Preview Tool Download JLCONE Desktop—Get $524 Exclusive Coupons Download Now Products CNC Machining Materials Aluminum Aluminum 6061 Aluminum 7075 Steel SUS304 45# Steel Copper Brass - H59 Copper - T2 Plastic POM Polycarbonate (PC) ABS FR4 PMMA (Acrylic) Nylon - PA6 Bakelite Sheet Metal Materials Aluminum 5052 Stainless Steel 201 Stainless Steel 304 Cold Rolled Steel Galvanized Steel Sheet Materials Contact Us Online Chat> Mon-Fri: 24 hours, Sat: 9am-6pm, GMT+8 Email Us> Mon-Fri: 24 hours, Sat: 9am-6pm, GMT+8 WhatsApp> Mon-Fri: 24 hours, Sat: 9am-6pm, GMT+8 Support Help Center Get instant answers. 24/7 Available. Blog Support About Us Search 0 Order Now Blog Knowledge Hub Materials Design & Engineering Manufacturing Services Blog Blog Knowledge...",
  "text_hash": "3abc3710cfe62b4f840e18bdbb9840a07144e884",
  "title": "Depth of Cut in CNC Machining: Calculation & Optimization",
  "url": "https://jlccnc.com/blog/depth-of-cut"
}