{
  "canonical": "",
  "category": "content",
  "competitor": "PCBWay",
  "ctas": [
    {
      "href": "/orderonline.aspx",
      "text": "PCB Instant Quote"
    },
    {
      "href": "javascript:void(0)",
      "text": "Sign Up"
    },
    {
      "href": "/project/shareproject/?order=1",
      "text": "By Source Files"
    },
    {
      "href": "/project/shareproject/?order=1",
      "text": "View all source files projects"
    },
    {
      "href": "/project/shareproject/?order=1",
      "text": "Source Files"
    },
    {
      "href": "/blog/club-publish.html",
      "text": "Submit for Publication"
    },
    {
      "href": "/blog/Activities/Submit_for_Publication___Now_I_Write_Articles_in_PCBWay.html",
      "text": "Write for PCBWay"
    },
    {
      "href": "/blog/?tag=PCB industry",
      "text": "PCB industry"
    },
    {
      "href": "/contact.html",
      "text": "Contact us"
    }
  ],
  "fetched_at": "2026-07-23T04:39:11+00:00",
  "h1": "How to Generate Gerber Files in Fusion 360?",
  "headings": [
    {
      "level": "h1",
      "text": "How to Generate Gerber Files in Fusion 360?"
    },
    {
      "level": "h3",
      "text": "Method One: Click on \"CAM Preview\" to Initiate the Export"
    },
    {
      "level": "h3",
      "text": "Method Two: Click on \"CAM Processor\" to Initiate the Export"
    },
    {
      "level": "h3",
      "text": "Method Three: Click on \"Export Gerber, NC Drill, Assembly and Drawing Outputs\" to Initiate the Export"
    },
    {
      "level": "h3",
      "text": "Online Gerber Files Viewer by PCBWay"
    },
    {
      "level": "h3",
      "text": "Related articles"
    }
  ],
  "images": [
    {
      "alt": "",
      "src": "/project/img/images/avatar/user-pic.png"
    },
    {
      "alt": "",
      "src": "/project/img/images/loading-pro.gif"
    },
    {
      "alt": "",
      "src": "https://pcbwayfile.s3.us-west-2.amazonaws.com/web/23/10/03/1152415436848m.jpeg"
    },
    {
      "alt": "",
      "src": "https://pcbwayfile.s3.us-west-2.amazonaws.com/web/25/02/01/195239553dd028d967de6453aa74b91ac0e5423e73248m.png"
    },
    {
      "alt": "",
      "src": "https://pcbwayfile.s3-us-west-2.amazonaws.com/web/21/08/30/1823256917346m.png"
    },
    {
      "alt": "",
      "src": "https://pcbwayfile.s3.us-west-2.amazonaws.com/web/23/11/23/1021264855557t.png"
    },
    {
      "alt": "",
      "src": "https://pcbwayfile.s3.us-west-2.amazonaws.com/web/23/11/23/1022249550427t.png"
    },
    {
      "alt": "",
      "src": "https://pcbwayfile.s3.us-west-2.amazonaws.com/web/23/11/23/1022430268886t.png"
    },
    {
      "alt": "",
      "src": "https://pcbwayfile.s3.us-west-2.amazonaws.com/web/23/11/23/1023020468175t.png"
    },
    {
      "alt": "",
      "src": "https://pcbwayfile.s3.us-west-2.amazonaws.com/web/23/11/23/1023260384860t.png"
    },
    {
      "alt": "",
      "src": "https://pcbwayfile.s3.us-west-2.amazonaws.com/web/23/11/23/1023370456450t.png"
    },
    {
      "alt": "",
      "src": "https://pcbwayfile.s3.us-west-2.amazonaws.com/web/23/11/23/1023542754745t.png"
    },
    {
      "alt": "",
      "src": "https://pcbwayfile.s3.us-west-2.amazonaws.com/web/23/11/23/1024077338187t.png"
    },
    {
      "alt": "",
      "src": "https://pcbwayfile.s3.us-west-2.amazonaws.com/web/23/11/23/1024208214087t.png"
    },
    {
      "alt": "",
      "src": "https://pcbwayfile.s3.us-west-2.amazonaws.com/web/23/11/23/1024328588742t.png"
    },
    {
      "alt": "",
      "src": "https://pcbwayfile.s3.us-west-2.amazonaws.com/web/23/11/23/1028317341731t.png"
    },
    {
      "alt": "",
      "src": "https://pcbwayfile.s3.us-west-2.amazonaws.com/web/23/11/23/1028395454002t.png"
    },
    {
      "alt": "",
      "src": "https://pcbwayfile.s3.us-west-2.amazonaws.com/web/23/11/23/1025341372037t.png"
    },
    {
      "alt": "",
      "src": "/img/images/note-tips.png"
    }
  ],
  "meta_description": "",
  "requested_url": "https://www.pcbway.com/blog/PCB_Design_Tutorial/How_to_Generate_Gerber_Files_in_Fusion_360_7c039fbf.html",
  "sections": [
    {
      "hash": "82aa87a7de3f0cde8d78846a3b459dd89e52c043",
      "heading": "How to Generate Gerber Files in Fusion 360?",
      "level": "h1",
      "text": "Blog > How to Generate Gerber Files in Fusion 360? How to Generate Gerber Files in Fusion 360? by: Mia Nov 23,2023 17051 Views 0 Comments Posted in PCB Design Tutorial Gerber Fusion 360 Autodesk Once you have completed the PCB design in Fusion 360, the next step is to export production files to prepare for PCB manufacturing. Therefore, this tutorial will guide you on how to export Gerber files and Drill files in Autodesk Fusion 360. This guide uses the demo board example in Fusion 360 named \"Air_Quality_Sensor.\" In Fusion 360, there are three options for exporting Gerber files: CAM Preview, CAM Processor, and Export Gerber, NC Drill, Assembly and Drawing Outputs. As shown in the following i..."
    },
    {
      "hash": "f7f31fb92c32f2d5bb6bfe1e69df59263239cd85",
      "heading": "Method One: Click on \"CAM Preview\" to Initiate the Export",
      "level": "h3",
      "text": "Once you have completed the PCB design in Fusion 360, the next step is to export production files to prepare for PCB manufacturing. Therefore, this tutorial will guide you on how to export Gerber files and Drill files in Autodesk Fusion 360. This guide uses the demo board example in Fusion 360 named \"Air_Quality_Sensor.\" In Fusion 360, there are three options for exporting Gerber files: CAM Preview, CAM Processor, and Export Gerber, NC Drill, Assembly and Drawing Outputs. As shown in the following image: Method One: Click on \"CAM Preview\" to Initiate the Export • Select \"MANUFACTURING\" -> \"MANUFACTURING\" -> \"CAM Preview\" • The Manufacturing Preview window will appear, then click on the CAM..."
    },
    {
      "hash": "f7f31fb92c32f2d5bb6bfe1e69df59263239cd85",
      "heading": "Method Two: Click on \"CAM Processor\" to Initiate the Export",
      "level": "h3",
      "text": "Once you have completed the PCB design in Fusion 360, the next step is to export production files to prepare for PCB manufacturing. Therefore, this tutorial will guide you on how to export Gerber files and Drill files in Autodesk Fusion 360. This guide uses the demo board example in Fusion 360 named \"Air_Quality_Sensor.\" In Fusion 360, there are three options for exporting Gerber files: CAM Preview, CAM Processor, and Export Gerber, NC Drill, Assembly and Drawing Outputs. As shown in the following image: Method One: Click on \"CAM Preview\" to Initiate the Export • Select \"MANUFACTURING\" -> \"MANUFACTURING\" -> \"CAM Preview\" • The Manufacturing Preview window will appear, then click on the CAM..."
    },
    {
      "hash": "f7f31fb92c32f2d5bb6bfe1e69df59263239cd85",
      "heading": "Method Three: Click on \"Export Gerber, NC Drill, Assembly and Drawing Outputs\" to Initiate the Export",
      "level": "h3",
      "text": "Once you have completed the PCB design in Fusion 360, the next step is to export production files to prepare for PCB manufacturing. Therefore, this tutorial will guide you on how to export Gerber files and Drill files in Autodesk Fusion 360. This guide uses the demo board example in Fusion 360 named \"Air_Quality_Sensor.\" In Fusion 360, there are three options for exporting Gerber files: CAM Preview, CAM Processor, and Export Gerber, NC Drill, Assembly and Drawing Outputs. As shown in the following image: Method One: Click on \"CAM Preview\" to Initiate the Export • Select \"MANUFACTURING\" -> \"MANUFACTURING\" -> \"CAM Preview\" • The Manufacturing Preview window will appear, then click on the CAM..."
    },
    {
      "hash": "f7f31fb92c32f2d5bb6bfe1e69df59263239cd85",
      "heading": "Online Gerber Files Viewer by PCBWay",
      "level": "h3",
      "text": "Once you have completed the PCB design in Fusion 360, the next step is to export production files to prepare for PCB manufacturing. Therefore, this tutorial will guide you on how to export Gerber files and Drill files in Autodesk Fusion 360. This guide uses the demo board example in Fusion 360 named \"Air_Quality_Sensor.\" In Fusion 360, there are three options for exporting Gerber files: CAM Preview, CAM Processor, and Export Gerber, NC Drill, Assembly and Drawing Outputs. As shown in the following image: Method One: Click on \"CAM Preview\" to Initiate the Export • Select \"MANUFACTURING\" -> \"MANUFACTURING\" -> \"CAM Preview\" • The Manufacturing Preview window will appear, then click on the CAM..."
    },
    {
      "hash": "a3c5ee9b440e6ce95d672f719a34c568dc11842a",
      "heading": "Related articles",
      "level": "h3",
      "text": "Related articles How to generate Gerber files from CircuitMaker 2.2.1.6? How to Export Gerber Files in DesignSpark PCB V11.0.0? How to add a Board Outline to Gerber Plots in DesignSpark PCB V11.0.0? How to Generate Gerber Files in Fusion 360?"
    }
  ],
  "status": 200,
  "structure_hash": "0cc8125957f17d39df1b9c7b4bbe3f17f776f125",
  "text_excerpt": "How to Generate Gerber Files in Fusion 360? - PCB Design Tutorial - PCBway PCBWay Community Search title or content Search PCBWay PCB Instant Quote CNC | 3D Printing Login Sign Up More Notifications No notifications. My Profile My projects My Likes My Deals My Goods for Bazaar Settings Sign Out Projects Categories DIY Electronics Arduino Hardware Audio Computers & USB Breakout Board Projects Home Automation LED Displays & Matrices IoT Robotics View all categories By Source Files Onju Voice - AI assistant replacement to Google Nest Mini by @justLV LogicAnalyzer V6.0 DIY 1kW Open Source MPPT Solar Charge Controller Tad Boy Color SummerCart64 - a fully open source N64 flashcart kv4p HT v1.7b QuinLED-Dig-Uno Bike Fingerprint - PCB Arduino RC engine sound & light controller with inertia simulation for ESP32 Solar Powered WiFi Weather Station V2.0 Frog Boy Color SIDKick pico 0.2 (SID 6581/8580-replacement for C64/C128) View all source files projects Featured Projects Onju Voice - AI assistant replacement to Google Nest Mini by @justLV LogicAnalyzer V6.0 DIY 1kW Open Source MPPT Solar Charge Controller Featured Source Files Video View all projects Questions Sponsorships Feedback Blog Sto...",
  "text_hash": "66a42e1161ac52f2bee8c9b0f52ad6073d9e3b11",
  "title": "How to Generate Gerber Files in Fusion 360? - PCB Design Tutorial - PCBway",
  "url": "https://www.pcbway.com/blog/PCB_Design_Tutorial/How_to_Generate_Gerber_Files_in_Fusion_360_7c039fbf.html"
}