{
  "canonical": "",
  "category": "service",
  "competitor": "Xometry",
  "ctas": [
    {
      "href": "",
      "text": "Get an Instant Quote"
    },
    {
      "href": "/capabilities/injection-molding-quote/",
      "text": "Injection Molding Services"
    },
    {
      "href": "/hardware-startups/",
      "text": "Hardware Startups"
    },
    {
      "href": "/capabilities/",
      "text": "Xometry Production Guide"
    },
    {
      "href": "https://community.xometry.com/kb",
      "text": "FAQs"
    },
    {
      "href": "https://community.xometry.com/",
      "text": "Supplier Community"
    },
    {
      "href": "/contact-us/",
      "text": "Contact Us"
    },
    {
      "href": "mailto:support@xometry.com",
      "text": "support@xometry.com"
    },
    {
      "href": "https://community.xometry.com/kb",
      "text": "Help Center"
    },
    {
      "href": "/xometry-enterprise/",
      "text": "Xometry Enterprise"
    },
    {
      "href": "/xometry-enterprise/teamspace/",
      "text": "Discover Xometry Teamspace"
    },
    {
      "href": "/xometry-enterprise/xometry-integration-punchout/",
      "text": "eProcurement Integrations"
    },
    {
      "href": "/xometry-enterprise/production-quotes/",
      "text": "Bulk Upload for Production Quotes"
    },
    {
      "href": "/xometry-enterprise/onboard-xometry/",
      "text": "Onboard Xometry As Your Vendor"
    },
    {
      "href": "/quoting/home/",
      "text": "Xometry's Platform"
    },
    {
      "href": "/how-xometry-works/",
      "text": "How to Use the Xometry Instant Quoting Engine®"
    },
    {
      "href": "/testdrive/",
      "text": "Test Drive Xometry"
    },
    {
      "href": "/how-xometry-works/tool-details/",
      "text": "Tool Library and Tool Detail Pages"
    },
    {
      "href": "https://community.xometry.com/",
      "text": "From Our FAQ"
    },
    {
      "href": "https://community.xometry.com/kb/articles/839-part-revisions-same-suppliers-for-repeat-orders",
      "text": "Part Revisions & Same-Suppliers for Repeat Orders"
    },
    {
      "href": "https://community.xometry.com/kb/articles/689-are-my-uploaded-files-and-xometry-projects-secure",
      "text": "Xometry's Privacy and Security"
    },
    {
      "href": "/about-us/",
      "text": "About Xometry"
    },
    {
      "href": "/quality-lab/",
      "text": "Xometry’s Quality Assurance"
    },
    {
      "href": "/manufacturing-partner-network-overview/",
      "text": "Xometry’s Supplier Network"
    },
    {
      "href": "/machine-learning-for-manufacturing/",
      "text": "Xometry's Machine Learning"
    },
    {
      "href": "/capabilities/community/",
      "text": "Xometry's Manufacturing Community"
    },
    {
      "href": "",
      "text": "Start Your New Instant Quote"
    },
    {
      "href": "https://community.xometry.com/kb/articles/651",
      "text": "learn more"
    },
    {
      "href": "",
      "text": "Get Your Instant Quote"
    },
    {
      "href": "https://www.xometry.com/capabilities/cnc-machining-service/",
      "text": "CNC Machining"
    },
    {
      "href": "https://www.xometry.com/capabilities/3d-printing-service/",
      "text": "3D Printing"
    },
    {
      "href": "https://www.xometry.com/capabilities/sheet-metal-fabrication/",
      "text": "Sheet Metal Fabrication"
    },
    {
      "href": "https://www.xometry.com/capabilities/injection-molding-service/",
      "text": "Injection Molding"
    },
    {
      "href": "https://www.xometry.com/capabilities/die-casting-services/",
      "text": "Metal Forming & Die Casting"
    },
    {
      "href": "https://www.xometry.com/xometry-enterprise/",
      "text": "Enterprise"
    },
    {
      "href": "https://www.xometry.com/aerospace-and-defense/",
      "text": "Aerospace & Defense"
    },
    {
      "href": "https://www.xometry.com/automotive/",
      "text": "Automotive"
    },
    {
      "href": "https://www.xometry.com/medical-and-dental/",
      "text": "Medical & Dental"
    },
    {
      "href": "https://www.xometry.com/electronics-and-semiconductors/",
      "text": "Electronics & Semiconductors"
    },
    {
      "href": "https://www.xometry.com/data-centers/",
      "text": "Data Centers"
    },
    {
      "href": "https://www.xometry.com/about-us/",
      "text": "About"
    },
    {
      "href": "https://www.xometry.com/careers",
      "text": "Careers"
    },
    {
      "href": "https://investors.xometry.com/news-and-events/news-releases",
      "text": "Press"
    },
    {
      "href": "https://investors.xometry.com/",
      "text": "Investor Relations"
    },
    {
      "href": "https://www.xometry.com/legal/",
      "text": "Legal"
    },
    {
      "href": "https://www.xometry.com/technical-resources/",
      "text": "Technical Hub"
    },
    {
      "href": "https://www.xometry.com/resources/design-guides/",
      "text": "Design Guides"
    },
    {
      "href": "https://www.xometry.com/get-started/",
      "text": "Get Started"
    },
    {
      "href": "https://www.xometry.com/resources/case-studies/",
      "text": "Case Studies"
    },
    {
      "href": "https://www.xometry.com/materials/",
      "text": "Materials Guide"
    },
    {
      "href": "https://www.xometry.com/finishes/",
      "text": "Finishes Guide"
    },
    {
      "href": "https://www.xometry.com/manufacturing-standards/",
      "text": "Manufacturing Standards"
    },
    {
      "href": "https://www.xometry.com/cad-add-ins/",
      "text": "CAD Add-ins"
    },
    {
      "href": "https://www.xometry.com/release-notes/",
      "text": "Release Notes"
    },
    {
      "href": "https://www.xometry.com/manufacturing-partner-network-overview/",
      "text": "Xometry Partner Network"
    },
    {
      "href": "https://www.xometry.com/become-a-supplier/",
      "text": "Become a Supplier"
    },
    {
      "href": "https://www.xometry.com/workcenter/",
      "text": "Workcenter"
    },
    {
      "href": "https://www.xometry.com/manufacturing-partner-network-overview/",
      "text": "Supplier Network"
    },
    {
      "href": "https://www.xometry.com/quality-lab/",
      "text": "Quality Assurance"
    },
    {
      "href": "https://www.xometry.com/certifications/",
      "text": "Certifications"
    }
  ],
  "fetched_at": "2026-07-16T04:24:40+00:00",
  "h1": "Plastic 3D Printing Service",
  "headings": [
    {
      "level": "h1",
      "text": "Plastic 3D Printing Service"
    },
    {
      "level": "h3",
      "text": "Plastic 3D Printing with Xometry"
    },
    {
      "level": "h3",
      "text": "Thermoplastic 3D Printing"
    },
    {
      "level": "h3",
      "text": "Resin 3D Printing"
    },
    {
      "level": "h3",
      "text": "Ready to get started on your custom Plastic 3D Printing quote?"
    },
    {
      "level": "h3",
      "text": "Applications of Plastic 3D Printing"
    },
    {
      "level": "h3",
      "text": "Advantages of Plastic 3D Printing"
    },
    {
      "level": "h3",
      "text": "Why Choose Xometry for Plastic 3D Printing?"
    },
    {
      "level": "h3",
      "text": "Multi Jet Fusion (MJF) Design Guide"
    }
  ],
  "images": [
    {
      "alt": "",
      "src": "data:image/svg+xml;charset=utf-8,%3Csvg%20height='492'%20width='492'%20xmlns='http://www.w3.org/2000/svg'%20version='1.1'%3E%3C/svg%3E"
    },
    {
      "alt": "Xometry X-Tile made from 3D printed Nylon.",
      "src": "https://images.prismic.io/xometry-marketing/Z9rbWziBA97GiqSa_PA12-Natural-no-bg.png?auto=format%2Ccompress&rect=1%2C0%2C2167%2C2167&w=492&h=492&fit=max"
    },
    {
      "alt": "",
      "src": "data:image/svg+xml;charset=utf-8,%3Csvg%20height='225'%20width='300'%20xmlns='http://www.w3.org/2000/svg'%20version='1.1'%3E%3C/svg%3E"
    },
    {
      "alt": "SLS Nylon Parts",
      "src": "https://images.prismic.io/xometry-marketing/4fdf61d2-3300-4636-83c7-aec207f29f0d_SLS+nylon+materials.jpg?auto=format%2Ccompress&fit=max&w=300&h=225"
    },
    {
      "alt": "",
      "src": "data:image/svg+xml;charset=utf-8,%3Csvg%20height='300'%20width='300'%20xmlns='http://www.w3.org/2000/svg'%20version='1.1'%3E%3C/svg%3E"
    },
    {
      "alt": "MJF Materials",
      "src": "https://images.prismic.io/xometry-marketing/Z9rifziBA97Giqbg_MJFMixMaterialsandFinish-Edit.png?auto=format%2Ccompress&fit=max&w=300&h=300"
    },
    {
      "alt": "FDM Part",
      "src": "https://images.prismic.io/xometry-marketing/642d2c3e-e8e9-4cac-b259-2111e8fa2fdb_fdm-part.png?auto=format%2Ccompress&fit=max&w=235&h=235"
    },
    {
      "alt": "",
      "src": "data:image/svg+xml;charset=utf-8,%3Csvg%20height='200'%20width='300'%20xmlns='http://www.w3.org/2000/svg'%20version='1.1'%3E%3C/svg%3E"
    },
    {
      "alt": "Stereolithography SLA materials have a variety of engineered properties for function and cosmetics",
      "src": "https://images.prismic.io/xometry-marketing/17a44386-0a6c-49d5-a8cc-063fa4de7a94_SLA+3D+Printing+Stereolithography+Mix+Materials.jpg?auto=compress%2Cformat&fit=max&w=300&h=200"
    },
    {
      "alt": "Xometry Capability",
      "src": "https://images.prismic.io/xometry-marketing/f43059be-7bef-4377-979f-2282bf729ca6_PolyJet-X-Rainbow-Kickstand-%283%29.jpg?auto=format%2Ccompress&rect=-888%2C-853%2C2688%2C2016&w=30..."
    },
    {
      "alt": "",
      "src": "data:image/svg+xml;charset=utf-8,%3Csvg%20height='169'%20width='300'%20xmlns='http://www.w3.org/2000/svg'%20version='1.1'%3E%3C/svg%3E"
    },
    {
      "alt": "Carbon Digital Light Synthesis (DLS) makes production parts without tooling",
      "src": "https://images.prismic.io/xometry-marketing/437e8983-e2cf-4248-a327-77e0d3e94290_Carbon+DLS+RPU+70+Build.jpg?auto=format%2Ccompress&fit=max&w=300&h=169"
    },
    {
      "alt": "Xometry Image",
      "src": "https://xometry-marketing.cdn.prismic.io/xometry-marketing/d8f64c17-2539-478c-8c19-80ca920f4796_3D-Printing-FNL+icon.svg?fit=max"
    },
    {
      "alt": "",
      "src": "data:image/svg+xml;charset=utf-8,%3Csvg%20height='185'%20width='185'%20xmlns='http://www.w3.org/2000/svg'%20version='1.1'%3E%3C/svg%3E"
    },
    {
      "alt": "Xometry Illustration",
      "src": "https://images.prismic.io/xometry-marketing/1930f975-a2c5-4e2f-890a-fc5a92f95f58_SLS.png?auto=compress%2Cformat&fit=max&w=185&h=185"
    },
    {
      "alt": "Xometry Illustration",
      "src": "https://images.prismic.io/xometry-marketing/7a0538d8-968c-415f-8696-d7863adfa434_Rapid_Prototyping.png?auto=compress%2Cformat&fit=max&w=185&h=185"
    },
    {
      "alt": "Xometry Illustration",
      "src": "https://images.prismic.io/xometry-marketing/bd35db8e-7c5f-4ef3-86be-2a2345b66b7b_unnamed+%2819%29.png?auto=compress%2Cformat&fit=max&w=185&h=185"
    },
    {
      "alt": "Xometry Resources",
      "src": "https://images.prismic.io/xometry-marketing/Z9rifziBA97Giqbg_MJFMixMaterialsandFinish-Edit.png?auto=format%2Ccompress&rect=0%2C0%2C4354%2C4354&w=492&h=492&fit=max"
    },
    {
      "alt": "Xometry Illustration",
      "src": "https://images.prismic.io/xometry-marketing/e7b66d54-0ac4-4ed2-9b4c-62db1c46b06c_Endless-Options.png?auto=compress%2Cformat&fit=max&w=185&h=185"
    },
    {
      "alt": "Xometry Illustration",
      "src": "https://images.prismic.io/xometry-marketing/c408f978-3fa0-45f1-ada7-8f03d93ce758_Project-Management.png?auto=compress%2Cformat&fit=max&w=185&h=185"
    },
    {
      "alt": "Xometry Illustration",
      "src": "https://images.prismic.io/xometry-marketing/25bb3ed3-9ce7-45db-a9cf-a4fea96ae2e8_Vetted-Network.png?auto=compress%2Cformat&fit=max&w=185&h=185"
    },
    {
      "alt": "Isometric illustration of the HP Multi Jet Fusion (MJF) printing process.",
      "src": "https://xometry-marketing.cdn.prismic.io/xometry-marketing/5f696773-1cfd-4918-8357-8a1d330fb247_HP-Multijet-Fusion.svg?fit=max"
    },
    {
      "alt": "Xometry Inc.",
      "src": "https://xometry-marketing.cdn.prismic.io/xometry-marketing/aUF6cHNYClf9oRtQ_Xometry_Light_Registered.svg?fit=max"
    },
    {
      "alt": "",
      "src": "https://xometry-marketing.cdn.prismic.io/xometry-marketing/afJuYcBOoF08xc3I_instagram.svg?fit=max"
    },
    {
      "alt": "",
      "src": "https://xometry-marketing.cdn.prismic.io/xometry-marketing/afJuYsBOoF08xc3J_linkedin-in.svg?fit=max"
    },
    {
      "alt": "",
      "src": "https://xometry-marketing.cdn.prismic.io/xometry-marketing/afJuY8BOoF08xc3K_youtube.svg?fit=max"
    },
    {
      "alt": "",
      "src": "https://xometry-marketing.cdn.prismic.io/xometry-marketing/afNddsBOoF08xf6h_xometry-logo-mark.svg?fit=max"
    },
    {
      "alt": "",
      "src": "https://xometry-marketing.cdn.prismic.io/xometry-marketing/afJtesBOoF08xc20_shield-halved.svg?fit=max"
    }
  ],
  "meta_description": "Plastic 3D Printing Services from Xometry help engineers make high-quality parts fast. We offer instant quotes, massive capacity, great prices, and guaranteed quality across six plastic 3D printing processes.",
  "requested_url": "https://www.xometry.com/capabilities/3d-printing-service/plastic",
  "sections": [
    {
      "hash": "4dc9ac336f9fa13d94825957bedbc63fda685959",
      "heading": "Plastic 3D Printing Service",
      "level": "h1",
      "text": "Plastic 3D Printing Service Plastic Prototypes and Production Parts in as Fast as 1 Day | Free Shipping on All US Orders | International prototype pricing includes tariffs . See How It Works"
    },
    {
      "hash": "6e6b8a0591ca94e73da5b673c0f5bc1bba780c90",
      "heading": "Plastic 3D Printing with Xometry",
      "level": "h3",
      "text": "Plastic 3D Printing with Xometry Plastic 3D printing is one of the fastest and most cost-effective methods available for the iterative design, prototyping, and production of custom parts with Xometry. Rather than the material being removed from stock, as with subtractive manufacturing processes such as CNC machining , 3D printing works by repeatedly layering small amounts of plastic to build a design from the ground up. This is done by providing the 3D plastic printers with a three-dimensional digital design file, commonly referred to as a computer-aided design (CAD) file. Once you have a CAD file for your design, there are a number of different 3D plastic printing methods that can be used..."
    },
    {
      "hash": "1c578087a18068c7bc5c3e3d5785dd5f5959a3d5",
      "heading": "Thermoplastic 3D Printing",
      "level": "h3",
      "text": "Thermoplastic 3D Printing Selective Laser Sintering (SLS) 3D Printing Service Quality prototypes and production parts | Rapid turnaround | Free shipping on all US and international orders | ISO 9001:2015, ISO 13485, IATF 16949:2016, and AS9100D certified. Start Your New Instant Quote Selective Laser Sintering (SLS) 3D Printing Service HP Multi Jet Fusion (MJF) 3D Printing Service Quality prototypes and production parts. Free shipping on all US and international orders. ISO 9001:2015, ISO 13485, IATF 16949:2016, and AS9100D certified. Start Your New Instant Quote HP Multi Jet Fusion (MJF) 3D Printing Service Fused Deposition Modeling (FDM) 3D Printing Service High-Quality Large Format FDM 3D..."
    },
    {
      "hash": "a91fd8b42ee32ea64d06a61e635f672b096363f3",
      "heading": "Resin 3D Printing",
      "level": "h3",
      "text": "Resin 3D Printing Stereolithography (SLA) 3D Printing Services High Detail, Smooth Surfaced Parts in Days Free shipping on all US 3D printing orders Start Your New Instant Quote Stereolithography (SLA) 3D Printing Services PolyJet 3D Printing Service Prototypes, full-color concept models, and simulated overmold parts in days | Free shipping on all US orders Start Your New Instant Quote PolyJet 3D Printing Service Carbon Digital Light Synthesis™ (DLS™) 3D Printing Service High-Performing Prototypes and Serialized Production Parts | Free Shipping on All US Orders Start Your New Instant Quote Carbon Digital Light Synthesis™ (DLS™) 3D Printing Service"
    },
    {
      "hash": "3b03a1ebbfd8dba90e6f9850c1160a5bbbfed96c",
      "heading": "Ready to get started on your custom Plastic 3D Printing quote?",
      "level": "h3",
      "text": "Ready to get started on your custom Plastic 3D Printing quote? Free shipping available for domestic 3D printing orders ; learn more ! Get Your Instant Quote"
    },
    {
      "hash": "4405e47c58696bfbf97aedd1b2a9bde5adfcb163",
      "heading": "Applications of Plastic 3D Printing",
      "level": "h3",
      "text": "Applications of Plastic 3D Printing Concept Models The speed and versatility of plastic 3D printing let product developers create physical snapshots of their designs through the iterative process. Rapid Prototyping Plastic 3D printing can be used to create fully-functional plastic prototypes, complete with moving parts, as well as all-in-one assemblies. Direct Digital Manufacturing The high accuracy and consistency of plastic 3D Printing make it an ideal way to build large quantities of discrete or customized parts."
    },
    {
      "hash": "e25344d38258d23bf3e173dc260a5400386ae60a",
      "heading": "Advantages of Plastic 3D Printing",
      "level": "h3",
      "text": "Advantages of Plastic 3D Printing Precision: We use the latest generation of 3D printing technologies to meet demanding tolerances Scalability: Whether it is one, or thousands, Xometry has the 3D printing capacity to meet your needs and lead time Durability: With engineered materials like nylon, polycarbonate, or even ULTEM, 3D printed plastic parts are tough and functional Rapid Turnaround: Get parts in as quick as 1 business day Complex Geometries: 3D printing can create complex parts without increased costs Low Cost: 3D printing is inexpensive and has no minimum order quantities"
    },
    {
      "hash": "723212233b1395beaa6113f727efd03a2ec187e6",
      "heading": "Why Choose Xometry for Plastic 3D Printing?",
      "level": "h3",
      "text": "Why Choose Xometry for Plastic 3D Printing? Endless Options Choose from millions of possible combinations of materials, finishes, tolerances, markings, and certifications for your order. Easy to Use Get your parts delivered right to your door without the hassle of sourcing, project management, logistics, or shipping. Vetted Network We are ISO 9001:2015, ISO 13485, and AS9100D certified. Only the top shops that apply to become Suppliers make it through our qualification process."
    },
    {
      "hash": "637829c6b436f416736789db54a225eb3617bf65",
      "heading": "Multi Jet Fusion (MJF) Design Guide",
      "level": "h3",
      "text": "Multi Jet Fusion (MJF) Design Guide See all our guides Get the Guide"
    }
  ],
  "status": 200,
  "structure_hash": "e0a5b4fa6e44ab6730824bf2312051cb6ee85b04",
  "text_excerpt": "Plastic 3D Printing | Custom Parts & Prototypes Get an Instant Quote Solutions Additive Manufacturing 3D Printing Service Plastic 3D Printing Service Fused Deposition Modeling HP Multi Jet Fusion Selective Laser Sintering Stereolithography PolyJet Production 3D Printing Service Carbon DLS Metal 3D Printing Service Direct Metal Laser Sintering Metal Binder Jetting Vapor Smoothing 3D Prints CNC Machining CNC Machining CNC Milling CNC Turning CNC Routing Swiss-type Turning Micro Machining Sheet and Tube Fabrication Sheet Metal Fabrication Sheet Cutting Laser Cutting Waterjet Cutting Laser Tube Cutting Tube Bending Injection Molding Injection Molding Services Plastic Injection Molding Prototype Molding Production Molding Insert Molding Overmolding Micro Molding Other Plastic Production Urethane and Silicone Casting Compression Molding Plastic Extrusion Metal Part Production Die Casting Metal Stamping Metal Extrusion Value-Added Solutions Assembly Services Weldments Rapid Prototyping High-Volume Production Precision Grinding Surface Grinding Powder Coating Industries Industries We Serve Aerospace and Defense Automotive Consumer Products Data Centers Design Agencies Education Electronic...",
  "text_hash": "9dfd0be9f42f25b332944ac995fa90ea0640e865",
  "title": "Plastic 3D Printing | Custom Parts & Prototypes",
  "url": "https://www.xometry.com/capabilities/3d-printing-service/plastic"
}