{
  "canonical": "https://www.fictiv.com/articles/jdm-odm-oem-manufacturing-models",
  "category": "content",
  "competitor": "Fictiv",
  "ctas": [
    {
      "href": "https://www.fictiv.com/articles/fictiv-receives-2026-supplytech-breakthrough-award",
      "text": "Learn More"
    },
    {
      "href": "/our-platform",
      "text": "Try the Platform"
    },
    {
      "href": "#",
      "text": "Got a Complex Program? Talk to Our Team"
    },
    {
      "href": "/production",
      "text": "Start Production"
    },
    {
      "href": "/help/getting-started",
      "text": "Getting Started"
    },
    {
      "href": "/help/getting-a-quote",
      "text": "Getting a quote"
    },
    {
      "href": "/help/placing-an-order",
      "text": "Placing an order"
    },
    {
      "href": "/help/uploading-and-organizing-parts",
      "text": "Uploading and organizing parts"
    },
    {
      "href": "/shows-and-events",
      "text": "Shows and Events Join us for an upcoming trade show or webinar. Learn more"
    },
    {
      "href": "/newsroom",
      "text": "Press Read the latest news about Fictiv and access our Press Kit Learn more"
    },
    {
      "href": "/careers",
      "text": "Careers We're hiring! Explore opportunities to join the Fictiv team! Learn more"
    },
    {
      "href": "/contact-us",
      "text": "Contact Us Our team is on stand by, waiting to assist you. Learn more"
    },
    {
      "href": "https://www.fictiv.com/signup",
      "text": "Get an instant quote"
    },
    {
      "href": "https://www.fictiv.com/signup",
      "text": "Get Instant Quote"
    },
    {
      "href": "/our-platform",
      "text": "Learn more"
    },
    {
      "href": "/production",
      "text": "Learn more"
    },
    {
      "href": "/case-studies/honeywell",
      "text": "Learn more"
    },
    {
      "href": "/ai/materials",
      "text": "Try Materials.Ai"
    },
    {
      "href": "https://www.fictiv.com/signup",
      "text": "instant quote"
    },
    {
      "href": "https://www.fictiv.com/authors/david_willson",
      "text": "Learn More »"
    },
    {
      "href": "https://www.fictiv.com/why-choose-fictiv/fictiv-vs-xometry",
      "text": "Xometry Alternative"
    },
    {
      "href": "https://www.fictiv.com/contact-us",
      "text": "Contact Us | NDA Form"
    },
    {
      "href": "/contact-us#nda",
      "text": "Non-Disclosure Agreement"
    },
    {
      "href": "/wp-content/uploads/2024/12/ISO9001-certificate-2024-2027.pdf",
      "text": "ISO 9001:2015 Certificate"
    }
  ],
  "fetched_at": "2026-07-22T04:36:06+00:00",
  "h1": "OEM vs. ODM vs. JDM: Key Manufacturing Models Explained for Scalable Product Development",
  "headings": [
    {
      "level": "h3",
      "text": "Quick Links"
    },
    {
      "level": "h1",
      "text": "OEM vs. ODM vs. JDM: Key Manufacturing Models Explained for Scalable Product Development"
    },
    {
      "level": "h2",
      "text": "Your Material Selection Assistant"
    },
    {
      "level": "h2",
      "text": "What Is OEM (Original Equipment Manufacturer)?"
    },
    {
      "level": "h3",
      "text": "Pros and Cons of OEM"
    },
    {
      "level": "h2",
      "text": "What Is ODM (Original Design Manufacturer)?"
    },
    {
      "level": "h3",
      "text": "Pros and Cons of ODM"
    },
    {
      "level": "h2",
      "text": "What Is JDM (Joint Design Manufacturer)?"
    },
    {
      "level": "h3",
      "text": "Pros and Cons of JDM"
    },
    {
      "level": "h2",
      "text": "Comparison: OEM vs. ODM vs. JDM"
    },
    {
      "level": "h2",
      "text": "When to Use Each Model"
    },
    {
      "level": "h3",
      "text": "When to Use OEM"
    },
    {
      "level": "h3",
      "text": "When to Use ODM"
    },
    {
      "level": "h3",
      "text": "When to Use JDM"
    },
    {
      "level": "h2",
      "text": "Benefits of Digital Manufacturing in JDM, ODM, and OEM Models"
    },
    {
      "level": "h3",
      "text": "Accelerated Prototyping"
    },
    {
      "level": "h3",
      "text": "Improved Supply Chain Transparency"
    },
    {
      "level": "h3",
      "text": "Risk Mitigation Through DFX and Early Validation"
    },
    {
      "level": "h3",
      "text": "Seamless Collaboration Across Teams and Time Zones"
    },
    {
      "level": "h3",
      "text": "Support Across All Models"
    },
    {
      "level": "h2",
      "text": "Choosing the Right Model—Backed by the Right Partner"
    },
    {
      "level": "h2",
      "text": "SIGN UP FOR OUR NEWSLETTER"
    },
    {
      "level": "h2",
      "text": "20% OFF YOUR FIRST ORDER"
    },
    {
      "level": "h3",
      "text": "YOU MIGHT ALSO BE INTERESTED IN"
    },
    {
      "level": "h3",
      "text": "U.S. Manufacturing Reaches Record $2.91 Trillion as Workforce Gap Threatens Next Decade of Growth"
    },
    {
      "level": "h3",
      "text": "Injection Molding Cycle Time: What Drives It and How to Reduce It"
    }
  ],
  "images": [
    {
      "alt": "fictiv",
      "src": "https://www.fictiv.com/wp-content/themes/fictiv-theme/assets/images/logos/fictiv-teal.svg"
    },
    {
      "alt": "Why Choose Fictiv?",
      "src": "https://www.fictiv.com/wp-content/themes/fictiv-theme/assets/images/navigation/our-platform-nav.webp"
    },
    {
      "alt": "Whats Next",
      "src": "https://www.fictiv.com/wp-content/themes/fictiv-theme/assets/images/navigation/nav-whatsnext-img.webp"
    },
    {
      "alt": "Navigation arrow down",
      "src": "https://www.fictiv.com/wp-content/themes/fictiv-theme/assets/images/navigation/nav-honeywell-case-study.webp"
    },
    {
      "alt": "",
      "src": "https://www.fictiv.com/wp-content/themes/fictiv-theme/assets/images/navigation/som26_featured_thumb.webp"
    },
    {
      "alt": "",
      "src": "https://www.fictiv.com/wp-content/themes/fictiv-theme/assets/images/navigation/Fictiv_nightside_thumbnail.jpg"
    },
    {
      "alt": "",
      "src": "https://www.fictiv.com/wp-content/themes/fictiv-theme/assets/images/navigation/Injection-molding-design-1.jpg"
    },
    {
      "alt": "Out Platform",
      "src": "https://www.fictiv.com/wp-content/themes/fictiv-theme/assets/images/navigation/our-platform-nav.webp"
    },
    {
      "alt": "",
      "src": "https://www.fictiv.com/wp-content/themes/fictiv-theme/assets/images/navigation/SOM_featured_thumb.jpg"
    },
    {
      "alt": "",
      "src": "https://www.fictiv.com/wp-content/themes/fictiv-theme/assets/images/navigation/fictiv-airvine-nav.png"
    },
    {
      "alt": "",
      "src": "https://www.fictiv.com/wp-content/themes/fictiv-theme/assets/images/navigation/MaterialsAI2.png"
    },
    {
      "alt": "mechstack phone",
      "src": "https://www.fictiv.com/wp-content/themes/fictiv-theme/assets/images/graphics/mechstack-phone-sidebar.png"
    },
    {
      "alt": "Your Material Selection Assistant",
      "src": "https://www.fictiv.com/wp-content/themes/fictiv-theme/assets/images/material-ai.webp"
    },
    {
      "alt": "Head-and-shoulders portrait of a smiling man in a navy blazer in a bright office setting.",
      "src": "https://www.fictiv.com/wp-content/uploads/2026/07/image3-40x40.jpg"
    },
    {
      "alt": "the type of manufacturing partnership and collaboration you use is an important business decision.",
      "src": "https://www.fictiv.com/wp-content/uploads/2025/05/JDM-manufacturing.jpg"
    },
    {
      "alt": "OEM original equipment manufacturer.",
      "src": "https://www.fictiv.com/wp-content/uploads/2025/05/JDM-OEM.jpg"
    },
    {
      "alt": "Choosing between OEM, ODM, and JDM manufacturing models comes down to company requirements and preferences.",
      "src": "https://www.fictiv.com/wp-content/uploads/2025/05/JDM-blocks.jpg"
    },
    {
      "alt": "Intellectual property is an important aspect of a manufacturing model.",
      "src": "https://www.fictiv.com/wp-content/uploads/2025/05/JDM-intellectual-property.jpg"
    },
    {
      "alt": "A digital manufacturing partner is a great solution to gaining benefits of various manufacturing models.",
      "src": "https://www.fictiv.com/wp-content/uploads/2025/05/JDM-handshake.jpg"
    },
    {
      "alt": "",
      "src": "https://www.fictiv.com/wp-content/uploads/2026/07/us_workforce_gap_web_thumnail_v1-copy.webp"
    },
    {
      "alt": "",
      "src": "https://www.fictiv.com/wp-content/uploads/2026/07/Injection-Molding-Process-Cycle-768x521.jpeg"
    },
    {
      "alt": "Fictiv misumi logo green",
      "src": "https://www.fictiv.com/wp-content/themes/fictiv-theme/assets/images/logos/fictiv-misumi.svg"
    }
  ],
  "meta_description": "Explore the differences between OEM, ODM, and JDM models and how digital manufacturing combines their strengths to accelerate scalable product development.",
  "requested_url": "https://www.fictiv.com/articles/jdm-odm-oem-manufacturing-models",
  "sections": [],
  "status": 200,
  "structure_hash": "aeb8461fb4234b3b87590b5ec421b757ac807afa",
  "text_excerpt": "JDM vs ODM vs OEM: Key Manufacturing Models Explained Fictiv named Sourcing Solution of the Year at the SupplyTech Breakthrough Awards → Learn More Fictiv named Sourcing Solution of the Year at the SupplyTech Breakthrough Awards → Learn More x Capabilities Capabilities CNC Machining Tight tolerances and finishing capabilities, manufactured in one day. Sheet Metal Experience the versatility & cost efficiency with flexible application options. Injection Molding Production-grade steel tooling, as fast as weeks. Die Casting Create high quality custom mechanicals with precision and accuracy. 3D Printing FDM, SLS, SLA, PolyJet, MJF technologies. Compression Molding Experience lower tooling costs with high-quality durable parts. Urethane Casting Production quality parts without the tooling investment. Explore All Capabilities Explore all materials and finishes View tolerances and specifications Smart Manufacturing Platform See how our digital platform gives you instant quoting, auto DFM tools, global & domestic options, and complete order visibility. Try the Platform Solutions Solutions Prototyping Quality Management Production Tariff Management Teams Why Choose Fictiv? Assembly & Weldin...",
  "text_hash": "4935f9b6b62a50707a96e0ff2cf80ac4a74cb63d",
  "title": "JDM vs ODM vs OEM: Key Manufacturing Models Explained",
  "url": "https://www.fictiv.com/articles/jdm-odm-oem-manufacturing-models"
}